<?xml version="1.0" encoding="UTF-8"?>
<objects serializationModel="Studio.02.02.00">
	<object class="Workspace" id="{d2e06f55-1985-4b7f-9515-178dca11ef99}">
		<property name="builtBanksOutputDirectory">
			<value>../../Assets/Audio/Banks</value>
		</property>
		<relationship name="masterEventFolder">
			<destination>{c7e67ed2-c518-46a8-b942-58acf1f3562d}</destination>
		</relationship>
		<relationship name="masterTagFolder">
			<destination>{dad2043b-aec1-4e91-990a-3003202fc98c}</destination>
		</relationship>
		<relationship name="masterEffectPresetFolder">
			<destination>{5c816c0a-8de4-4bad-b96c-57e62da3ad9b}</destination>
		</relationship>
		<relationship name="masterParameterPresetFolder">
			<destination>{a01a4fc1-381f-459c-ad9a-652e8220ad13}</destination>
		</relationship>
		<relationship name="masterBankFolder">
			<destination>{873f386b-6859-420c-9fbc-b1defdd8a492}</destination>
		</relationship>
		<relationship name="masterSandboxFolder">
			<destination>{6991794b-b463-4e7a-9a06-91708ac6a2d6}</destination>
		</relationship>
		<relationship name="masterAssetFolder">
			<destination>{f1cf931f-c99e-4d9d-b421-20fbd678ee6a}</destination>
		</relationship>
		<relationship name="mixer">
			<destination>{b5da4278-b91a-48d2-86fa-270a94816727}</destination>
		</relationship>
		<relationship name="profilerSessionFolder">
			<destination>{d5bcbe49-45b5-4bc7-b808-3728aedd1a00}</destination>
		</relationship>
		<relationship name="platforms">
			<destination>{46523e97-04ef-494f-9f76-c19a85292d8a}</destination>
		</relationship>
	</object>
</objects>
